palamedes/__init__.py
palamedes/__main__.py
palamedes/align.py
palamedes/config.py
palamedes/models.py
palamedes/test_palamedes.py
palamedes/utils.py
palamedes/hgvs/__init__.py
palamedes/hgvs/builders.py
palamedes/hgvs/utils.py
tests/__init__.py
tests/base.py
tests/test_align.py
tests/test_models.py
tests/test_utils.py
tests/hgvs/__init__.py
tests/hgvs/test_builders.py
tests/hgvs/test_utils.py
palamedes-0.0.9.dist-info/LICENSE.txt
palamedes-0.0.9.dist-info/METADATA
palamedes-0.0.9.dist-info/WHEEL
palamedes-0.0.9.dist-info/entry_points.txt
palamedes-0.0.9.dist-info/top_level.txt
palamedes-0.0.9.dist-info/RECORD
