Metadata-Version: 2.1
Name: palamedes
Version: 0.0.9
Summary: Palamedes: HGVS variants from a sequence alignment
Home-page: https://github.com/mammothbio-os/palamedes
Author-email: open-source@mammothbiosci.com
Keywords: bioinformatics,alignment,hgvs,variant,amino acid
Classifier: Development Status :: 3 - Alpha
Classifier: License :: OSI Approved :: MIT License
Classifier: Programming Language :: Python :: 3.11
Requires-Python: >=3.11
License-File: LICENSE.txt
Requires-Dist: biopython ~=1.83
Requires-Dist: hgvs ~=1.5.4
